YTRequests/__init__.py
YTRequests/ytrequests.py
YTRequests-1.0.3.dist-info/LICENSE
YTRequests-1.0.3.dist-info/METADATA
YTRequests-1.0.3.dist-info/WHEEL
YTRequests-1.0.3.dist-info/top_level.txt
YTRequests-1.0.3.dist-info/RECORD
