Metadata-Version: 2.1
Name: YTRequests
Version: 1.0.3
Summary: UNKNOWN
Home-page: https://github.com/tsubasa652/python-YTRequests
Author: tsubasa652
Author-email: mail@tsubasa.ml
Maintainer-email: mail@tsubasa.ml
License: MIT
Download-URL: https://github.com/tsubasa652/python-YTRequests
Platform: UNKNOWN
License-File: LICENSE
Requires-Dist: requests
